relink/__init__.py
relink/client.py
tests/__init__.py
tests/test_client.py
relink-0.0.1.dist-info/METADATA
relink-0.0.1.dist-info/WHEEL
relink-0.0.1.dist-info/top_level.txt
relink-0.0.1.dist-info/RECORD
