Metadata-Version: 2.1
Name: relink
Version: 0.0.1
Summary: A client for https://rel.ink/ API
Home-page: UNKNOWN
Author: Romain Ardiet
Author-email: romardie@publicisgroupe.net
License: Apache 2.0
Platform: UNKNOWN
Classifier: Development Status :: 5 - Production/Stable
Classifier: Topic :: Internet :: WWW/HTTP
Classifier: Topic :: Internet :: WWW/HTTP :: Site Management :: Link Checking
Classifier: Environment :: Console
Classifier: Environment :: Web Environment
Classifier: Intended Audience :: Developers
Classifier: Programming Language :: Python :: 3.5
Classifier: Programming Language :: Python :: 3.6
Classifier: Programming Language :: Python :: 3.7
Classifier: Programming Language :: Python :: 3.8
Classifier: License :: OSI Approved :: Apache Software License
Classifier: Operating System :: OS Independent
Requires-Dist: requests
Provides-Extra: dev
Requires-Dist: requests-mock ; extra == 'dev'
